baserowapi/__init__.py
baserowapi/baserow.py
baserowapi/exceptions.py
baserowapi/models/__init__.py
baserowapi/models/filter.py
baserowapi/models/row.py
baserowapi/models/table.py
baserowapi/models/fields/__init__.py
baserowapi/models/fields/base_date_field.py
baserowapi/models/fields/base_text_class.py
baserowapi/models/fields/boolean_field.py
baserowapi/models/fields/count_field.py
baserowapi/models/fields/created_on_field.py
baserowapi/models/fields/date_field.py
baserowapi/models/fields/email_field.py
baserowapi/models/fields/field.py
baserowapi/models/fields/field_list.py
baserowapi/models/fields/file_field.py
baserowapi/models/fields/formula_field.py
baserowapi/models/fields/generic_field.py
baserowapi/models/fields/last_modified_field.py
baserowapi/models/fields/long_text_field.py
baserowapi/models/fields/lookup_field.py
baserowapi/models/fields/multiple_collaborators_field.py
baserowapi/models/fields/multiple_select_field.py
baserowapi/models/fields/number_field.py
baserowapi/models/fields/password_field.py
baserowapi/models/fields/phone_number_field.py
baserowapi/models/fields/rating_field.py
baserowapi/models/fields/single_select_field.py
baserowapi/models/fields/table_link_field.py
baserowapi/models/fields/text_field.py
baserowapi/models/fields/url_field.py
baserowapi/models/row_values/__init__.py
baserowapi/models/row_values/base_date_row_value.py
baserowapi/models/row_values/boolean_row_value.py
baserowapi/models/row_values/count_row_value.py
baserowapi/models/row_values/created_on_row_value.py
baserowapi/models/row_values/date_row_value.py
baserowapi/models/row_values/email_row_value.py
baserowapi/models/row_values/file_row_value.py
baserowapi/models/row_values/formula_row_value.py
baserowapi/models/row_values/generic_row_value.py
baserowapi/models/row_values/last_modified_row_value.py
baserowapi/models/row_values/long_text_row_value.py
baserowapi/models/row_values/lookup_row_value.py
baserowapi/models/row_values/multiple_collaborators_row_value.py
baserowapi-0.1.0b4.dist-info/LICENSE
baserowapi-0.1.0b4.dist-info/METADATA
baserowapi-0.1.0b4.dist-info/WHEEL
baserowapi-0.1.0b4.dist-info/top_level.txt
baserowapi-0.1.0b4.dist-info/RECORD
