Metadata-Version: 2.1
Name: baserowapi
Version: 0.1.0b4
Summary: API wrapper for Baserow
Home-page: https://github.com/jimwitte/baserowapi
Author: James P Witte
Author-email: jim@thunderingbison.com
License: GPLv3
Classifier: Development Status :: 4 - Beta
Classifier: Intended Audience :: Developers
Classifier: License :: OSI Approved :: GNU General Public License v3 (GPLv3)
Classifier: Programming Language :: Python :: 3
Classifier: Programming Language :: Python :: 3.10
Requires-Python: >=3.10
License-File: LICENSE
Requires-Dist: pytz>=2023.3.post1
Requires-Dist: Requests~=2.31
